ssakz.py
ssakz-0.1.2.dist-info/LICENSE
ssakz-0.1.2.dist-info/METADATA
ssakz-0.1.2.dist-info/WHEEL
ssakz-0.1.2.dist-info/top_level.txt
ssakz-0.1.2.dist-info/RECORD
